chuk_motion/__init__.py
chuk_motion/async_server.py
chuk_motion/server.py
chuk_motion/video_manager.py
chuk_motion/components/__init__.py
chuk_motion/components/base.py
chuk_motion/components/component_helpers.py
chuk_motion/components/animations/__init__.py
chuk_motion/components/animations/Counter/__init__.py
chuk_motion/components/animations/Counter/builder.py
chuk_motion/components/animations/Counter/schema.py
chuk_motion/components/animations/Counter/tool.py
chuk_motion/components/animations/LayoutEntrance/__init__.py
chuk_motion/components/animations/LayoutEntrance/builder.py
chuk_motion/components/animations/LayoutEntrance/renderer.py
chuk_motion/components/animations/LayoutEntrance/schema.py
chuk_motion/components/animations/LayoutEntrance/tool.py
chuk_motion/components/animations/PanelCascade/__init__.py
chuk_motion/components/animations/PanelCascade/builder.py
chuk_motion/components/animations/PanelCascade/renderer.py
chuk_motion/components/animations/PanelCascade/schema.py
chuk_motion/components/animations/PanelCascade/tool.py
chuk_motion/components/charts/__init__.py
chuk_motion/components/charts/AreaChart/__init__.py
chuk_motion/components/charts/AreaChart/builder.py
chuk_motion/components/charts/AreaChart/schema.py
chuk_motion/components/charts/AreaChart/tool.py
chuk_motion/components/charts/BarChart/__init__.py
chuk_motion/components/charts/BarChart/builder.py
chuk_motion/components/charts/BarChart/schema.py
chuk_motion/components/charts/BarChart/tool.py
chuk_motion/components/charts/DonutChart/__init__.py
chuk_motion/components/charts/DonutChart/builder.py
chuk_motion/components/charts/DonutChart/schema.py
chuk_motion/components/charts/DonutChart/tool.py
chuk_motion/components/charts/HorizontalBarChart/__init__.py
chuk_motion/components/charts/HorizontalBarChart/builder.py
chuk_motion/components/charts/HorizontalBarChart/schema.py
chuk_motion/components/charts/HorizontalBarChart/tool.py
chuk_motion/components/charts/LineChart/__init__.py
chuk_motion-0.2.0.dist-info/METADATA
chuk_motion-0.2.0.dist-info/WHEEL
chuk_motion-0.2.0.dist-info/entry_points.txt
chuk_motion-0.2.0.dist-info/top_level.txt
chuk_motion-0.2.0.dist-info/RECORD
