Metadata-Version: 2.4
Name: chuk-motion
Version: 0.2.0
Summary: Remotion MCP Server - A design-system-first approach to AI-powered video generation
Author: Chris Hay
Requires-Python: >=3.11
Requires-Dist: pydantic>=2.11.7
Requires-Dist: aiofiles>=23.0.0
Requires-Dist: jinja2>=3.1.0
Requires-Dist: pyyaml>=6.0.0
Requires-Dist: chuk-virtual-fs>=0.2.2
Requires-Dist: chuk-mcp-server>=0.15.1
Requires-Dist: chuk-artifacts>=0.10
Provides-Extra: dev
Requires-Dist: pytest>=8.0.0; extra == "dev"
Requires-Dist: pytest-asyncio>=0.24.0; extra == "dev"
Requires-Dist: pytest-cov>=5.0.0; extra == "dev"
Requires-Dist: pytest-mock>=3.10.0; extra == "dev"
Requires-Dist: ruff>=0.3.0; extra == "dev"
Requires-Dist: mypy>=1.9.0; extra == "dev"
Requires-Dist: black>=23.0.0; extra == "dev"
Requires-Dist: types-pyyaml>=6.0.0; extra == "dev"
